apicurioregistrysdk/__init__.py
apicurioregistrysdk/client/.kiota.log
apicurioregistrysdk/client/admin/admin_request_builder.py
apicurioregistrysdk/client/admin/config/artifact_types/artifact_types_request_builder.py
apicurioregistrysdk/client/admin/config/config_request_builder.py
apicurioregistrysdk/client/admin/config/properties/item/with_property_name_item_request_builder.py
apicurioregistrysdk/client/admin/config/properties/properties_request_builder.py
apicurioregistrysdk/client/admin/export/export_request_builder.py
apicurioregistrysdk/client/admin/import_/import_request_builder.py
apicurioregistrysdk/client/admin/role_mappings/item/with_principal_item_request_builder.py
apicurioregistrysdk/client/admin/role_mappings/role_mappings_request_builder.py
apicurioregistrysdk/client/admin/rules/item/with_rule_type_item_request_builder.py
apicurioregistrysdk/client/admin/rules/rules_request_builder.py
apicurioregistrysdk/client/admin/snapshots/snapshots_request_builder.py
apicurioregistrysdk/client/groups/groups_request_builder.py
apicurioregistrysdk/client/groups/item/artifacts/artifacts_request_builder.py
apicurioregistrysdk/client/groups/item/artifacts/item/branches/branches_request_builder.py
apicurioregistrysdk/client/groups/item/artifacts/item/branches/item/versions/versions_request_builder.py
apicurioregistrysdk/client/groups/item/artifacts/item/branches/item/with_branch_item_request_builder.py
apicurioregistrysdk/client/groups/item/artifacts/item/rules/item/with_rule_type_item_request_builder.py
apicurioregistrysdk/client/groups/item/artifacts/item/rules/rules_request_builder.py
apicurioregistrysdk/client/groups/item/artifacts/item/versions/item/comments/comments_request_builder.py
apicurioregistrysdk/client/groups/item/artifacts/item/versions/item/comments/item/with_comment_item_request_builder.py
apicurioregistrysdk/client/groups/item/artifacts/item/versions/item/content/content_request_builder.py
apicurioregistrysdk-3.1.2.dist-info/METADATA
apicurioregistrysdk-3.1.2.dist-info/WHEEL
apicurioregistrysdk-3.1.2.dist-info/RECORD
