Metadata-Version: 2.4
Name: apicurioregistrysdk
Version: 3.1.2
Summary: 
License: Apache 2.0
Keywords: apicurio,registry
Author: Andrea Peruffo
Author-email: andrea.peruffo1982@gmail.com
Requires-Python: >=3.9,<4.0
Classifier: License :: Other/Proprietary License
Classifier: Programming Language :: Python :: 3
Classifier: Programming Language :: Python :: 3.9
Classifier: Programming Language :: Python :: 3.10
Classifier: Programming Language :: Python :: 3.11
Classifier: Programming Language :: Python :: 3.12
Classifier: Programming Language :: Python :: 3.13
Classifier: Programming Language :: Python :: 3.14
Requires-Dist: microsoft-kiota-abstractions (>=1.3.3,<2.0.0)
Requires-Dist: microsoft-kiota-http (>=1.3.3,<2.0.0)
Requires-Dist: microsoft-kiota-serialization-form (>=0.1.1,<0.2.0)
Requires-Dist: microsoft-kiota-serialization-json (>=1.3.2,<2.0.0)
Requires-Dist: microsoft-kiota-serialization-multipart (>=0.1.0,<0.2.0)
Requires-Dist: microsoft-kiota-serialization-text (>=1.0.0,<2.0.0)
Project-URL: Homepage, https://github.com/apicurio/apicurio-registry
Project-URL: Repository, https://github.com/apicurio/apicurio-registry
